{
    "rekep_stage": 2,
    "joint_info": {
        "joint_positions": [
            0.007431602105498314,
            0.2839403748512268,
            -0.0037150103598833084,
            -2.1791796684265137,
            0.06792177259922028,
            2.633070945739746,
            0.37030312418937683
        ],
        "reset_joint_pos": [
            0.01559,
            -0.60356,
            -0.00596,
            -2.52428,
            -0.02803,
            1.89863,
            0.02934
        ]
    },
    "ee_info": {
        "position": [
            -0.2515656170654891,
            0.009293470943601279,
            0.5680932189944201
        ],
        "orientation": [
            -0.48240298473191945,
            -0.13733933630197703,
            -0.27552408687988983,
            0.8200681341052529
        ]
    },
    "gripper_info": {
        "state": 0.9779735803604126
    },
    "safety_info": {
        "collision_status": "false",
        "safety_status": "normal",
        "errors": []
    },
    "control_info": {
        "control_mode": "position",
        "operation_mode": "auto"
    },
    "misc": {
        "world2robot_homo": [
            [
                0.5012914810868776,
                -0.29392914747335336,
                0.8138258457774075,
                0.24424806735052013
            ],
            [
                -0.8651198042350154,
                -0.1882655619632068,
                0.4648911727480386,
                -0.4794940216693016
            ],
            [
                0.016570314121747254,
                -0.9371028409114263,
                -0.34865984891530166,
                0.4863975841602079
            ],
            [
                0.0,
                0.0,
                0.0,
                1.0
            ]
        ]
    }
}